{
    "color=white": {
        "hardness": {
            "minecraft:default": 6.25,
            "minecraft:wooden_pickaxe": 0.95,
            "minecraft:stone_pickaxe": 0.5,
            "minecraft:iron_pickaxe": 0.35,
            "minecraft:diamond_pickaxe": 0.25,
            "minecraft:golden_pickaxe": 0.2
        },
        "gravity": false,
        "burnability": 0,
        "light": 0,
        "light_needed": {
            
        },
        "tool_damage": {
            "minecraft:wooden_pickaxe": 1,
            "minecraft:stone_pickaxe": 1,
            "minecraft:iron_pickaxe": 1,
            "minecraft:diamond_pickaxe": 1,
            "minecraft:golden_pickaxe": 1
        },
        "solid_faces": {
            "down": true,
            "up": true,
            "north": true,
            "south": true,
            "east": true,
            "west": true
        },
        "need_support": {
            
        },
        "resistence": 30,
        "transparent": false,
        "solid": true,
        "hurt_on_touch": "",
        "piston_push": 1
        "sticky_push": 1,
        "fall_damage": 1,
        "hitbox": [
            {
                "from": [ 0, 0, 0 ],
                "to": [ 16, 16, 16 ]
            }
        ],
        "boundingbox": [
            {
                "from": [ 0, 0, 0 ],
                "to": [ 16, 16, 16 ]
            }
        ]
    },
    "color=orange": {
        "hardness": {
            "minecraft:default": 6.25,
            "minecraft:wooden_pickaxe": 0.95,
            "minecraft:stone_pickaxe": 0.5,
            "minecraft:iron_pickaxe": 0.35,
            "minecraft:diamond_pickaxe": 0.25,
            "minecraft:golden_pickaxe": 0.2
        },
        "gravity": false,
        "burnability": 0,
        "light": 0,
        "light_needed": {
            
        },
        "tool_damage": {
            "minecraft:wooden_pickaxe": 1,
            "minecraft:stone_pickaxe": 1,
            "minecraft:iron_pickaxe": 1,
            "minecraft:diamond_pickaxe": 1,
            "minecraft:golden_pickaxe": 1
        },
        "solid_faces": {
            "down": true,
            "up": true,
            "north": true,
            "south": true,
            "east": true,
            "west": true
        },
        "need_support": {
            
        },
        "resistence": 30,
        "transparent": false,
        "solid": true,
        "hurt_on_touch": "",
        "piston_push": 1
        "sticky_push": 1,
        "fall_damage": 1,
        "hitbox": [
            {
                "from": [ 0, 0, 0 ],
                "to": [ 16, 16, 16 ]
            }
        ],
        "boundingbox": [
            {
                "from": [ 0, 0, 0 ],
                "to": [ 16, 16, 16 ]
            }
        ]
    },
    "color=magenta": {
        "hardness": {
            "minecraft:default": 6.25,
            "minecraft:wooden_pickaxe": 0.95,
            "minecraft:stone_pickaxe": 0.5,
            "minecraft:iron_pickaxe": 0.35,
            "minecraft:diamond_pickaxe": 0.25,
            "minecraft:golden_pickaxe": 0.2
        },
        "gravity": false,
        "burnability": 0,
        "light": 0,
        "light_needed": {
            
        },
        "tool_damage": {
            "minecraft:wooden_pickaxe": 1,
            "minecraft:stone_pickaxe": 1,
            "minecraft:iron_pickaxe": 1,
            "minecraft:diamond_pickaxe": 1,
            "minecraft:golden_pickaxe": 1
        },
        "solid_faces": {
            "down": true,
            "up": true,
            "north": true,
            "south": true,
            "east": true,
            "west": true
        },
        "need_support": {
            
        },
        "resistence": 30,
        "transparent": false,
        "solid": true,
        "hurt_on_touch": "",
        "piston_push": 1
        "sticky_push": 1,
        "fall_damage": 1,
        "hitbox": [
            {
                "from": [ 0, 0, 0 ],
                "to": [ 16, 16, 16 ]
            }
        ],
        "boundingbox": [
            {
                "from": [ 0, 0, 0 ],
                "to": [ 16, 16, 16 ]
            }
        ]
    },
    "color=light_blue": {
        "hardness": {
            "minecraft:default": 6.25,
            "minecraft:wooden_pickaxe": 0.95,
            "minecraft:stone_pickaxe": 0.5,
            "minecraft:iron_pickaxe": 0.35,
            "minecraft:diamond_pickaxe": 0.25,
            "minecraft:golden_pickaxe": 0.2
        },
        "gravity": false,
        "burnability": 0,
        "light": 0,
        "light_needed": {
            
        },
        "tool_damage": {
            "minecraft:wooden_pickaxe": 1,
            "minecraft:stone_pickaxe": 1,
            "minecraft:iron_pickaxe": 1,
            "minecraft:diamond_pickaxe": 1,
            "minecraft:golden_pickaxe": 1
        },
        "solid_faces": {
            "down": true,
            "up": true,
            "north": true,
            "south": true,
            "east": true,
            "west": true
        },
        "need_support": {
            
        },
        "resistence": 30,
        "transparent": false,
        "solid": true,
        "hurt_on_touch": "",
        "piston_push": 1
        "sticky_push": 1,
        "fall_damage": 1,
        "hitbox": [
            {
                "from": [ 0, 0, 0 ],
                "to": [ 16, 16, 16 ]
            }
        ],
        "boundingbox": [
            {
                "from": [ 0, 0, 0 ],
                "to": [ 16, 16, 16 ]
            }
        ]
    },
    "color=yellow": {
        "hardness": {
            "minecraft:default": 6.25,
            "minecraft:wooden_pickaxe": 0.95,
            "minecraft:stone_pickaxe": 0.5,
            "minecraft:iron_pickaxe": 0.35,
            "minecraft:diamond_pickaxe": 0.25,
            "minecraft:golden_pickaxe": 0.2
        },
        "gravity": false,
        "burnability": 0,
        "light": 0,
        "light_needed": {
            
        },
        "tool_damage": {
            "minecraft:wooden_pickaxe": 1,
            "minecraft:stone_pickaxe": 1,
            "minecraft:iron_pickaxe": 1,
            "minecraft:diamond_pickaxe": 1,
            "minecraft:golden_pickaxe": 1
        },
        "solid_faces": {
            "down": true,
            "up": true,
            "north": true,
            "south": true,
            "east": true,
            "west": true
        },
        "need_support": {
            
        },
        "resistence": 30,
        "transparent": false,
        "solid": true,
        "hurt_on_touch": "",
        "piston_push": 1
        "sticky_push": 1,
        "fall_damage": 1,
        "hitbox": [
            {
                "from": [ 0, 0, 0 ],
                "to": [ 16, 16, 16 ]
            }
        ],
        "boundingbox": [
            {
                "from": [ 0, 0, 0 ],
                "to": [ 16, 16, 16 ]
            }
        ]
    },
    "color=lime": {
        "hardness": {
            "minecraft:default": 6.25,
            "minecraft:wooden_pickaxe": 0.95,
            "minecraft:stone_pickaxe": 0.5,
            "minecraft:iron_pickaxe": 0.35,
            "minecraft:diamond_pickaxe": 0.25,
            "minecraft:golden_pickaxe": 0.2
        },
        "gravity": false,
        "burnability": 0,
        "light": 0,
        "light_needed": {
            
        },
        "tool_damage": {
            "minecraft:wooden_pickaxe": 1,
            "minecraft:stone_pickaxe": 1,
            "minecraft:iron_pickaxe": 1,
            "minecraft:diamond_pickaxe": 1,
            "minecraft:golden_pickaxe": 1
        },
        "solid_faces": {
            "down": true,
            "up": true,
            "north": true,
            "south": true,
            "east": true,
            "west": true
        },
        "need_support": {
            
        },
        "resistence": 30,
        "transparent": false,
        "solid": true,
        "hurt_on_touch": "",
        "piston_push": 1
        "sticky_push": 1,
        "fall_damage": 1,
        "hitbox": [
            {
                "from": [ 0, 0, 0 ],
                "to": [ 16, 16, 16 ]
            }
        ],
        "boundingbox": [
            {
                "from": [ 0, 0, 0 ],
                "to": [ 16, 16, 16 ]
            }
        ]
    },
    "color=pink": {
        "hardness": {
            "minecraft:default": 6.25,
            "minecraft:wooden_pickaxe": 0.95,
            "minecraft:stone_pickaxe": 0.5,
            "minecraft:iron_pickaxe": 0.35,
            "minecraft:diamond_pickaxe": 0.25,
            "minecraft:golden_pickaxe": 0.2
        },
        "gravity": false,
        "burnability": 0,
        "light": 0,
        "light_needed": {
            
        },
        "tool_damage": {
            "minecraft:wooden_pickaxe": 1,
            "minecraft:stone_pickaxe": 1,
            "minecraft:iron_pickaxe": 1,
            "minecraft:diamond_pickaxe": 1,
            "minecraft:golden_pickaxe": 1
        },
        "solid_faces": {
            "down": true,
            "up": true,
            "north": true,
            "south": true,
            "east": true,
            "west": true
        },
        "need_support": {
            
        },
        "resistence": 30,
        "transparent": false,
        "solid": true,
        "hurt_on_touch": "",
        "piston_push": 1
        "sticky_push": 1,
        "fall_damage": 1,
        "hitbox": [
            {
                "from": [ 0, 0, 0 ],
                "to": [ 16, 16, 16 ]
            }
        ],
        "boundingbox": [
            {
                "from": [ 0, 0, 0 ],
                "to": [ 16, 16, 16 ]
            }
        ]
    },
    "color=gray": {
        "hardness": {
            "minecraft:default": 6.25,
            "minecraft:wooden_pickaxe": 0.95,
            "minecraft:stone_pickaxe": 0.5,
            "minecraft:iron_pickaxe": 0.35,
            "minecraft:diamond_pickaxe": 0.25,
            "minecraft:golden_pickaxe": 0.2
        },
        "gravity": false,
        "burnability": 0,
        "light": 0,
        "light_needed": {
            
        },
        "tool_damage": {
            "minecraft:wooden_pickaxe": 1,
            "minecraft:stone_pickaxe": 1,
            "minecraft:iron_pickaxe": 1,
            "minecraft:diamond_pickaxe": 1,
            "minecraft:golden_pickaxe": 1
        },
        "solid_faces": {
            "down": true,
            "up": true,
            "north": true,
            "south": true,
            "east": true,
            "west": true
        },
        "need_support": {
            
        },
        "resistence": 30,
        "transparent": false,
        "solid": true,
        "hurt_on_touch": "",
        "piston_push": 1
        "sticky_push": 1,
        "fall_damage": 1,
        "hitbox": [
            {
                "from": [ 0, 0, 0 ],
                "to": [ 16, 16, 16 ]
            }
        ],
        "boundingbox": [
            {
                "from": [ 0, 0, 0 ],
                "to": [ 16, 16, 16 ]
            }
        ]
    },
    "color=silver": {
        "hardness": {
            "minecraft:default": 6.25,
            "minecraft:wooden_pickaxe": 0.95,
            "minecraft:stone_pickaxe": 0.5,
            "minecraft:iron_pickaxe": 0.35,
            "minecraft:diamond_pickaxe": 0.25,
            "minecraft:golden_pickaxe": 0.2
        },
        "gravity": false,
        "burnability": 0,
        "light": 0,
        "light_needed": {
            
        },
        "tool_damage": {
            "minecraft:wooden_pickaxe": 1,
            "minecraft:stone_pickaxe": 1,
            "minecraft:iron_pickaxe": 1,
            "minecraft:diamond_pickaxe": 1,
            "minecraft:golden_pickaxe": 1
        },
        "solid_faces": {
            "down": true,
            "up": true,
            "north": true,
            "south": true,
            "east": true,
            "west": true
        },
        "need_support": {
            
        },
        "resistence": 30,
        "transparent": false,
        "solid": true,
        "hurt_on_touch": "",
        "piston_push": 1
        "sticky_push": 1,
        "fall_damage": 1,
        "hitbox": [
            {
                "from": [ 0, 0, 0 ],
                "to": [ 16, 16, 16 ]
            }
        ],
        "boundingbox": [
            {
                "from": [ 0, 0, 0 ],
                "to": [ 16, 16, 16 ]
            }
        ]
    },
    "color=cyan": {
        "hardness": {
            "minecraft:default": 6.25,
            "minecraft:wooden_pickaxe": 0.95,
            "minecraft:stone_pickaxe": 0.5,
            "minecraft:iron_pickaxe": 0.35,
            "minecraft:diamond_pickaxe": 0.25,
            "minecraft:golden_pickaxe": 0.2
        },
        "gravity": false,
        "burnability": 0,
        "light": 0,
        "light_needed": {
            
        },
        "tool_damage": {
            "minecraft:wooden_pickaxe": 1,
            "minecraft:stone_pickaxe": 1,
            "minecraft:iron_pickaxe": 1,
            "minecraft:diamond_pickaxe": 1,
            "minecraft:golden_pickaxe": 1
        },
        "solid_faces": {
            "down": true,
            "up": true,
            "north": true,
            "south": true,
            "east": true,
            "west": true
        },
        "need_support": {
            
        },
        "resistence": 30,
        "transparent": false,
        "solid": true,
        "hurt_on_touch": "",
        "piston_push": 1
        "sticky_push": 1,
        "fall_damage": 1,
        "hitbox": [
            {
                "from": [ 0, 0, 0 ],
                "to": [ 16, 16, 16 ]
            }
        ],
        "boundingbox": [
            {
                "from": [ 0, 0, 0 ],
                "to": [ 16, 16, 16 ]
            }
        ]
    },
    "color=purple": {
        "hardness": {
            "minecraft:default": 6.25,
            "minecraft:wooden_pickaxe": 0.95,
            "minecraft:stone_pickaxe": 0.5,
            "minecraft:iron_pickaxe": 0.35,
            "minecraft:diamond_pickaxe": 0.25,
            "minecraft:golden_pickaxe": 0.2
        },
        "gravity": false,
        "burnability": 0,
        "light": 0,
        "light_needed": {
            
        },
        "tool_damage": {
            "minecraft:wooden_pickaxe": 1,
            "minecraft:stone_pickaxe": 1,
            "minecraft:iron_pickaxe": 1,
            "minecraft:diamond_pickaxe": 1,
            "minecraft:golden_pickaxe": 1
        },
        "solid_faces": {
            "down": true,
            "up": true,
            "north": true,
            "south": true,
            "east": true,
            "west": true
        },
        "need_support": {
            
        },
        "resistence": 30,
        "transparent": false,
        "solid": true,
        "hurt_on_touch": "",
        "piston_push": 1
        "sticky_push": 1,
        "fall_damage": 1,
        "hitbox": [
            {
                "from": [ 0, 0, 0 ],
                "to": [ 16, 16, 16 ]
            }
        ],
        "boundingbox": [
            {
                "from": [ 0, 0, 0 ],
                "to": [ 16, 16, 16 ]
            }
        ]
    },
    "color=blue": {
        "hardness": {
            "minecraft:default": 6.25,
            "minecraft:wooden_pickaxe": 0.95,
            "minecraft:stone_pickaxe": 0.5,
            "minecraft:iron_pickaxe": 0.35,
            "minecraft:diamond_pickaxe": 0.25,
            "minecraft:golden_pickaxe": 0.2
        },
        "gravity": false,
        "burnability": 0,
        "light": 0,
        "light_needed": {
            
        },
        "tool_damage": {
            "minecraft:wooden_pickaxe": 1,
            "minecraft:stone_pickaxe": 1,
            "minecraft:iron_pickaxe": 1,
            "minecraft:diamond_pickaxe": 1,
            "minecraft:golden_pickaxe": 1
        },
        "solid_faces": {
            "down": true,
            "up": true,
            "north": true,
            "south": true,
            "east": true,
            "west": true
        },
        "need_support": {
            
        },
        "resistence": 30,
        "transparent": false,
        "solid": true,
        "hurt_on_touch": "",
        "piston_push": 1
        "sticky_push": 1,
        "fall_damage": 1,
        "hitbox": [
            {
                "from": [ 0, 0, 0 ],
                "to": [ 16, 16, 16 ]
            }
        ],
        "boundingbox": [
            {
                "from": [ 0, 0, 0 ],
                "to": [ 16, 16, 16 ]
            }
        ]
    },
    "color=brown": {
        "hardness": {
            "minecraft:default": 6.25,
            "minecraft:wooden_pickaxe": 0.95,
            "minecraft:stone_pickaxe": 0.5,
            "minecraft:iron_pickaxe": 0.35,
            "minecraft:diamond_pickaxe": 0.25,
            "minecraft:golden_pickaxe": 0.2
        },
        "gravity": false,
        "burnability": 0,
        "light": 0,
        "light_needed": {
            
        },
        "tool_damage": {
            "minecraft:wooden_pickaxe": 1,
            "minecraft:stone_pickaxe": 1,
            "minecraft:iron_pickaxe": 1,
            "minecraft:diamond_pickaxe": 1,
            "minecraft:golden_pickaxe": 1
        },
        "solid_faces": {
            "down": true,
            "up": true,
            "north": true,
            "south": true,
            "east": true,
            "west": true
        },
        "need_support": {
            
        },
        "resistence": 30,
        "transparent": false,
        "solid": true,
        "hurt_on_touch": "",
        "piston_push": 1
        "sticky_push": 1,
        "fall_damage": 1,
        "hitbox": [
            {
                "from": [ 0, 0, 0 ],
                "to": [ 16, 16, 16 ]
            }
        ],
        "boundingbox": [
            {
                "from": [ 0, 0, 0 ],
                "to": [ 16, 16, 16 ]
            }
        ]
    },
    "color=green": {
        "hardness": {
            "minecraft:default": 6.25,
            "minecraft:wooden_pickaxe": 0.95,
            "minecraft:stone_pickaxe": 0.5,
            "minecraft:iron_pickaxe": 0.35,
            "minecraft:diamond_pickaxe": 0.25,
            "minecraft:golden_pickaxe": 0.2
        },
        "gravity": false,
        "burnability": 0,
        "light": 0,
        "light_needed": {
            
        },
        "tool_damage": {
            "minecraft:wooden_pickaxe": 1,
            "minecraft:stone_pickaxe": 1,
            "minecraft:iron_pickaxe": 1,
            "minecraft:diamond_pickaxe": 1,
            "minecraft:golden_pickaxe": 1
        },
        "solid_faces": {
            "down": true,
            "up": true,
            "north": true,
            "south": true,
            "east": true,
            "west": true
        },
        "need_support": {
            
        },
        "resistence": 30,
        "transparent": false,
        "solid": true,
        "hurt_on_touch": "",
        "piston_push": 1
        "sticky_push": 1,
        "fall_damage": 1,
        "hitbox": [
            {
                "from": [ 0, 0, 0 ],
                "to": [ 16, 16, 16 ]
            }
        ],
        "boundingbox": [
            {
                "from": [ 0, 0, 0 ],
                "to": [ 16, 16, 16 ]
            }
        ]
    },
    "color=red": {
        "hardness": {
            "minecraft:default": 6.25,
            "minecraft:wooden_pickaxe": 0.95,
            "minecraft:stone_pickaxe": 0.5,
            "minecraft:iron_pickaxe": 0.35,
            "minecraft:diamond_pickaxe": 0.25,
            "minecraft:golden_pickaxe": 0.2
        },
        "gravity": false,
        "burnability": 0,
        "light": 0,
        "light_needed": {
            
        },
        "tool_damage": {
            "minecraft:wooden_pickaxe": 1,
            "minecraft:stone_pickaxe": 1,
            "minecraft:iron_pickaxe": 1,
            "minecraft:diamond_pickaxe": 1,
            "minecraft:golden_pickaxe": 1
        },
        "solid_faces": {
            "down": true,
            "up": true,
            "north": true,
            "south": true,
            "east": true,
            "west": true
        },
        "need_support": {
            
        },
        "resistence": 30,
        "transparent": false,
        "solid": true,
        "hurt_on_touch": "",
        "piston_push": 1
        "sticky_push": 1,
        "fall_damage": 1,
        "hitbox": [
            {
                "from": [ 0, 0, 0 ],
                "to": [ 16, 16, 16 ]
            }
        ],
        "boundingbox": [
            {
                "from": [ 0, 0, 0 ],
                "to": [ 16, 16, 16 ]
            }
        ]
    },
    "color=black": {
        "hardness": {
            "minecraft:default": 6.25,
            "minecraft:wooden_pickaxe": 0.95,
            "minecraft:stone_pickaxe": 0.5,
            "minecraft:iron_pickaxe": 0.35,
            "minecraft:diamond_pickaxe": 0.25,
            "minecraft:golden_pickaxe": 0.2
        },
        "gravity": false,
        "burnability": 0,
        "light": 0,
        "light_needed": {
            
        },
        "tool_damage": {
            "minecraft:wooden_pickaxe": 1,
            "minecraft:stone_pickaxe": 1,
            "minecraft:iron_pickaxe": 1,
            "minecraft:diamond_pickaxe": 1,
            "minecraft:golden_pickaxe": 1
        },
        "solid_faces": {
            "down": true,
            "up": true,
            "north": true,
            "south": true,
            "east": true,
            "west": true
        },
        "need_support": {
            
        },
        "resistence": 30,
        "transparent": false,
        "solid": true,
        "hurt_on_touch": "",
        "piston_push": 1
        "sticky_push": 1,
        "fall_damage": 1,
        "hitbox": [
            {
                "from": [ 0, 0, 0 ],
                "to": [ 16, 16, 16 ]
            }
        ],
        "boundingbox": [
            {
                "from": [ 0, 0, 0 ],
                "to": [ 16, 16, 16 ]
            }
        ]
    }
}