{
    "ingredients": [
        {
            "items": [
                [
                    {
                        "item": "minecraft:banner",
                        "id": 0,
                        "conditions": {
                            "layers": {
                                "max": 15
                            }
                        }
                    }
                ]
            ]
        },
        {
            "items": [
                [
                    {
                        "item": "minecraft:notch_apple"
                    }
                ]
            ]
        },
        {
            "items": [
                [
                    {
                        "item": "minecraft:ink_sack"
                    }
                ]
            ]
        }
    ],
    "return": {
        "item": "minecraft:banner"
    },
    "group": "minecraft:banner_mojang",
    "functions": [
        {
            "function": "minecraft:copy_component",
            "id": 0
        },
        {
            "function": "minecraft:add_component",
            "banner": {
                "layer": {
                    "color": "black",
                    "pattern": "mojang"
                }
            }
        }
    ]
}