{
    "parent": "minecraft:3_items",
    "ingredients": [
        "item1": {
            "item": "minecraft:banner",
            "id": 0,
            "conditions": {
                "layers": {
                    "max": 15
                }
            }
        },
        "item2": {
            "item": "minecraft:notch_apple"
        },
        "item3": {
            "item": "minecraft:ink_sack"
        }
    ],
    "result": {
        "item": "minecraft:banner"
    },
    "group": "minecraft:banner_mojang",
    "functions": [
        {
            "function": "minecraft:copy_component",
            "id": 0
        },
        {
            "function": "minecraft:add_component",
            "banner": {
                "layer": {
                    "color": "black",
                    "pattern": "mojang"
                }
            }
        }
    ]
}