{
    "parent": "minecraft:banner_left_of_upsingrediente_down_diagonal",
    "ingredients": {
        "banner": {
            "item": "minecraft:banner",
            "conditions": {
                "layers": {
                    "max": 15
                }
            }
        },
        "dye": {
            "item": "minecraft:lime_dye"
        }
    },
    "result": {
        "item": "minecraft:banner"
    },
    "group": "minecraft:banner_left_of_upsingrediente_down_diagonal",
    "functions": [
        {
            "function": "minecraft:copy_component",
            "ingredient": "banner"
        },
        {
            "function": "minecraft:add_component",
            "banner": {
                "layer": {
                    "color": "lime",
                    "pattern": "left_of_upsingrediente_down_diagonal"
                }
            }
        }
    ]
}