{
    "ingredients": [
        {
            "items": [
                [
                    {
                        "item": "minecraft:diamond"
                    },
                    {
                        "item": "minecraft:diamond"
                    },
                    {
                        "item": "minecraft:diamond"
                    }
                ],
                [
                    {
                        "item": "minecraft:diamond"
                    },
                    {
                        
                    },
                    {
                        "item": "minecraft:diamond"
                    }
                ]
            ]
        }
    ],
    "return": {
        "item": "minecraft:diamond_helmet"
    },
	"group": "minecraft:helmet"
}