{
    "ingredients": [
        {
            "items": [
                [
                    {
                        "item": "minecraft:stick"
                    },
                    {
                        "item": "minecraft:jungle_planks"
                    },
                    {
                        "item": "minecraft:stick"
                    }
                ],
                [
                    {
                        "item": "minecraft:stick"
                    },
                    {
                        "item": "minecraft:jungle_planks"
                    },
                    {
                        "item": "minecraft:stick"
                    }
                ]
            ]
        }
    ],
    "return": {
        "item": "minecraft:jungle_fence_gate"
    },
    "group": "minecraft:fence_gate"
}