{
    "ingredients": [
        {
            "items": [
                [
                    {
                        "item": "minecraft:light_blue_dye"
                    }
                ]
            ]
        },
        {
            "items": [
                [
                    {
                        "item": "minecraft:white_bed"
                    }
                ]
            ]
        }
    ],
    "return": {
        "item": "minecraft:light_blue_bed"
    },
	"group": "minecraft:bed_coloring"
}