[
    {
        "ingredients": [
            {
                "items": [
                    [
                        {
                            "item": "minecraft:planks",
                            "data": 3
                        },
                        {
                            "item": "minecraft:planks",
                            "data": 3
                        }
                    ],
                    [
                        {
                            "item": "minecraft:planks",
                            "data": 3
                        },
                        {
                            "item": "minecraft:planks",
                            "data": 3
                        }
                    ],
                    [
                        {
                            "item": "minecraft:planks",
                            "data": 3
                        },
                        {
                            "item": "minecraft:planks",
                            "data": 3
                        }
                    ]
                ]
            }
        ],
        "return": {
            "amount": 3
        }
    }
]