[
    {
        "ingredients": [
            {
                "items": [
                    [
                        {
                            "item": "minecraft:book"
                        }
                    ]
                ]
            },
            {
                "items": [
                    [
                        {
                            "item": "minecraft:feather"
                        }
                    ]
                ]
            },
            {
                "items": [
                    [
                        {
                            "item": "minecraft:dye",
                            "data": 0
                        }
                    ]
                ]
            }
        ]
    }
]